infomatic/__init__.py
infomatic-0.0.1.dist-info/LICENSE
infomatic-0.0.1.dist-info/METADATA
infomatic-0.0.1.dist-info/WHEEL
infomatic-0.0.1.dist-info/top_level.txt
infomatic-0.0.1.dist-info/RECORD
