Metadata-Version: 2.1
Name: infomatic
Version: 0.0.1
Summary: personal database management
Home-page: https://example.com/infomatic
Author: Your Name
Author-email: your.email@example.com
Classifier: Programming Language :: Python :: 3
Classifier: License :: OSI Approved :: MIT License
Classifier: Operating System :: OS Independent
Requires-Python: >=3.6
License-File: LICENSE
